doppler_env.pth
doppler_env/__init__.py
doppler_env-0.3.1.dist-info/METADATA
doppler_env-0.3.1.dist-info/WHEEL
doppler_env-0.3.1.dist-info/top_level.txt
doppler_env-0.3.1.dist-info/RECORD
