Metadata-Version: 2.1
Name: doppler-env
Version: 0.3.1
Summary: Inject Doppler secrets as environment variables into your Python application during local development with debugging support for PyCharm and Visual Studio Code.
Home-page: https://github.com/dopplerhq/python-doppler-env
Author: Doppler
Author-email: support@doppler.com
License: APL 2.0
Project-URL: Bug Reports, https://github.com/dopplerhq/python-doppler-env/issues
Project-URL: Source, https://github.com/dopplerhq/python-doppler-env
Keywords: doppler,environment variables,app secrets,app config,os.environ
Classifier: Development Status :: 4 - Beta
Classifier: Intended Audience :: Developers
Classifier: Topic :: Software Development :: Build Tools
Classifier: Topic :: Utilities
Classifier: License :: OSI Approved :: Apache Software License
Classifier: Programming Language :: Python :: 3.6
Classifier: Programming Language :: Python :: 3.7
Classifier: Programming Language :: Python :: 3.8
Classifier: Programming Language :: Python :: 3.9
Classifier: Programming Language :: Python :: 3.10
Requires-Python: >=3.6
Requires-Dist: pip
Requires-Dist: python-dotenv
Provides-Extra: dev
Requires-Dist: check-manifest ; extra == 'dev'
Provides-Extra: test
